staff_auth/__init__.py
staff_auth/apps.py
staff_auth/backend.py
staff_auth/configured_settings.py
staff_auth/middleware.py
staff_auth/pipeline.py
staff_auth/urls.py
staff_auth/views.py
staff_auth/static/staff_auth/css/custom-login.css
staff_auth/static/staff_auth/css/page-styles.css
staff_auth/templates/admin/login.html
staff_auth/templates/staff_auth/auth-error.html
politico_staff_auth-0.0.5.dist-info/LICENSE
politico_staff_auth-0.0.5.dist-info/METADATA
politico_staff_auth-0.0.5.dist-info/WHEEL
politico_staff_auth-0.0.5.dist-info/top_level.txt
politico_staff_auth-0.0.5.dist-info/RECORD
