Metadata-Version: 2.1
Name: politico-staff-auth
Version: 0.0.5
Summary: Staff authentication via Slack, the POLITICO way.
Home-page: https://github.com/The-Politico/politico-staff-auth/
Author: POLITICO interactive news
Author-email: interactives@politico.com
License: MIT
Platform: UNKNOWN
Classifier: Development Status :: 3 - Alpha
Classifier: Framework :: Django
Classifier: Framework :: Django :: 2.0
Classifier: Intended Audience :: Developers
Classifier: Intended Audience :: Information Technology
Classifier: License :: OSI Approved :: MIT License
Classifier: Operating System :: OS Independent
Classifier: Programming Language :: Python :: 3
Classifier: Programming Language :: Python :: 3.5
Classifier: Programming Language :: Python :: 3.6
Classifier: Topic :: Internet :: WWW/HTTP
Requires-Dist: social-auth-core
Requires-Dist: social-auth-app-django
Provides-Extra: dev
Requires-Dist: ipython ; extra == 'dev'
Provides-Extra: test
Requires-Dist: pytest ; extra == 'test'
